{
  "id": 11,
  "name": "Ben Briggs",
  "tracks": [
    {
      "title": "Fearless Living",
      "ranked_modes": [
        "osu"
      ],
      "beatmapset_ids_by_mode": {
        "osu": [
          934415
        ]
      }
    },
    {
      "title": "Methods",
      "ranked_modes": [
        "osu"
      ],
      "beatmapset_ids_by_mode": {
        "osu": [
          948165
        ]
      }
    },
    {
      "title": "New Game Plus",
      "ranked_modes": [
        "osu"
      ],
      "beatmapset_ids_by_mode": {
        "osu": [
          934627
        ]
      }
    },
    {
      "title": "Selecting Continue",
      "ranked_modes": [
        "osu",
        "taiko"
      ],
      "beatmapset_ids_by_mode": {
        "taiko": [
          2397891
        ],
        "osu": [
          948868
        ]
      }
    },
    {
      "title": "Wave Island",
      "ranked_modes": [
        "osu"
      ],
      "beatmapset_ids_by_mode": {
        "osu": [
          934666
        ]
      }
    },
    {
      "title": "We Could Quest Together",
      "ranked_modes": [
        "osu"
      ],
      "beatmapset_ids_by_mode": {
        "osu": [
          903393
        ]
      }
    },
    {
      "title": "Why Are We Yelling",
      "ranked_modes": [
        "osu"
      ],
      "beatmapset_ids_by_mode": {
        "osu": [
          952380
        ]
      }
    },
    {
      "title": "Yes (Maybe)",
      "ranked_modes": [
        "fruits",
        "osu"
      ],
      "beatmapset_ids_by_mode": {
        "fruits": [
          964357
        ],
        "osu": [
          933940
        ]
      }
    },
    {
      "title": "Chrome City",
      "ranked_modes": [],
      "beatmapset_ids_by_mode": {}
    },
    {
      "title": "Deserted Path",
      "ranked_modes": [],
      "beatmapset_ids_by_mode": {}
    },
    {
      "title": "Dewdrop Jungle",
      "ranked_modes": [],
      "beatmapset_ids_by_mode": {}
    },
    {
      "title": "Don't Force It",
      "ranked_modes": [],
      "beatmapset_ids_by_mode": {}
    },
    {
      "title": "Don't Let It Go To Waste",
      "ranked_modes": [],
      "beatmapset_ids_by_mode": {}
    },
    {
      "title": "Earthbound Sounds",
      "ranked_modes": [],
      "beatmapset_ids_by_mode": {}
    },
    {
      "title": "Exposed and Unafraid",
      "ranked_modes": [],
      "beatmapset_ids_by_mode": {}
    },
    {
      "title": "Game Boy Color Envy",
      "ranked_modes": [],
      "beatmapset_ids_by_mode": {}
    },
    {
      "title": "Haunted Swamp",
      "ranked_modes": [],
      "beatmapset_ids_by_mode": {}
    },
    {
      "title": "It Must Use Force",
      "ranked_modes": [],
      "beatmapset_ids_by_mode": {}
    },
    {
      "title": "Long Lung",
      "ranked_modes": [],
      "beatmapset_ids_by_mode": {}
    },
    {
      "title": "Loopy Fruits",
      "ranked_modes": [],
      "beatmapset_ids_by_mode": {}
    },
    {
      "title": "Magmortar Tunnel",
      "ranked_modes": [],
      "beatmapset_ids_by_mode": {}
    },
    {
      "title": "Mystery Gift Radio!",
      "ranked_modes": [],
      "beatmapset_ids_by_mode": {}
    },
    {
      "title": "NES Funk",
      "ranked_modes": [],
      "beatmapset_ids_by_mode": {}
    },
    {
      "title": "No One's Watching",
      "ranked_modes": [],
      "beatmapset_ids_by_mode": {}
    },
    {
      "title": "Recurring Dreams",
      "ranked_modes": [],
      "beatmapset_ids_by_mode": {}
    },
    {
      "title": "Something Step",
      "ranked_modes": [],
      "beatmapset_ids_by_mode": {}
    },
    {
      "title": "This Track May Snack",
      "ranked_modes": [],
      "beatmapset_ids_by_mode": {}
    },
    {
      "title": "Try to Forget It",
      "ranked_modes": [],
      "beatmapset_ids_by_mode": {}
    },
    {
      "title": "Underground Headquarters",
      "ranked_modes": [],
      "beatmapset_ids_by_mode": {}
    },
    {
      "title": "You Overdid It",
      "ranked_modes": [],
      "beatmapset_ids_by_mode": {}
    }
  ],
  "updated_at": "2026-03-28T12:17:42Z"
}