{
  "id": 221,
  "name": "Tasty",
  "tracks": [
    {
      "title": "Aiobahn - Islands",
      "preview": "https://assets.ppy.sh/artists/221/Songs/Aiobahn - Islands.mp3",
      "ranked_modes": [],
      "beatmapset_ids_by_mode": {}
    },
    {
      "title": "F.O.O.L & Laura Brehm - Waking Up",
      "preview": "https://assets.ppy.sh/artists/221/Songs/F.O.O.L %26 Laura Brehm - Waking Up.mp3",
      "ranked_modes": [],
      "beatmapset_ids_by_mode": {}
    },
    {
      "title": "Grim Fables - Oasis VIP",
      "preview": "https://assets.ppy.sh/artists/221/Songs/Grim Fables - Oasis VIP.mp3",
      "ranked_modes": [],
      "beatmapset_ids_by_mode": {}
    },
    {
      "title": "oneohkay - Last 7 Letters",
      "preview": "https://assets.ppy.sh/artists/221/Songs/oneohkay - Last 7 Letters.mp3",
      "ranked_modes": [],
      "beatmapset_ids_by_mode": {}
    },
    {
      "title": "Rhodz - Fading Horizon (Nhato Remix) [feat. Auvic & Pipo Fernandez]",
      "preview": "https://assets.ppy.sh/artists/221/Songs/Rhodz - Fading Horizon (Nhato Remix) %5Bfeat. Auvic %26 Pipo Fernandez%5D.mp3",
      "ranked_modes": [],
      "beatmapset_ids_by_mode": {}
    },
    {
      "title": "Rhodz - Reflection of Happiness (feat. Colate)",
      "preview": "https://assets.ppy.sh/artists/221/Songs/Rhodz - Reflection of Happiness (feat. Colate).mp3",
      "ranked_modes": [],
      "beatmapset_ids_by_mode": {}
    },
    {
      "title": "Rhodz - Try Again",
      "preview": "https://assets.ppy.sh/artists/221/Songs/Rhodz - Try Again.mp3",
      "ranked_modes": [],
      "beatmapset_ids_by_mode": {}
    },
    {
      "title": "Shurk - A Place Only We Know feat. Pink Noise",
      "preview": "https://assets.ppy.sh/artists/221/Songs/Shurk - A Place Only We Know feat. Pink Noise.mp3",
      "ranked_modes": [],
      "beatmapset_ids_by_mode": {}
    },
    {
      "title": "Snail's House - First Love",
      "preview": "https://assets.ppy.sh/artists/221/Songs/Snail%27s House - First Love.mp3",
      "ranked_modes": [],
      "beatmapset_ids_by_mode": {}
    },
    {
      "title": "Snail's House - Grape Soda",
      "preview": "https://assets.ppy.sh/artists/221/Songs/Snail%27s House - Grape Soda.mp3",
      "ranked_modes": [],
      "beatmapset_ids_by_mode": {}
    },
    {
      "title": "Snail's House - Ma Chouchoute",
      "preview": "https://assets.ppy.sh/artists/221/Songs/Snail%27s House - Ma Chouchoute.mp3",
      "ranked_modes": [],
      "beatmapset_ids_by_mode": {}
    },
    {
      "title": "Snail's House - Ma Chouchoute (Cut Ver.)",
      "preview": "https://assets.ppy.sh/artists/221/Songs/Snails_House_-_Ma_Chouchoute_Cut_Ver..mp3",
      "ranked_modes": [],
      "beatmapset_ids_by_mode": {}
    },
    {
      "title": "Snail's House - Pixel Dream",
      "preview": "https://assets.ppy.sh/artists/221/Songs/Snail%27s House - Pixel Dream.mp3",
      "ranked_modes": [],
      "beatmapset_ids_by_mode": {}
    },
    {
      "title": "Snail's House - Sparkle",
      "preview": "https://assets.ppy.sh/artists/221/Songs/Snail%27s House - Sparkle.mp3",
      "ranked_modes": [],
      "beatmapset_ids_by_mode": {}
    }
  ],
  "updated_at": "2026-04-02T03:26:17Z"
}