{
  "id": 353,
  "name": "Stars Hollow",
  "tracks": [
    {
      "title": "as you were before.",
      "preview": "https://assets.ppy.sh/artists/353/Happy Again (Deluxe)/Stars Hollow - as you were before..mp3",
      "ranked_modes": [
        "osu",
        "taiko"
      ],
      "beatmapset_ids_by_mode": {
        "osu": [
          1966575
        ],
        "taiko": [
          1509638
        ]
      }
    },
    {
      "title": "It's Not That",
      "preview": "https://assets.ppy.sh/artists/353/Happy Again (Deluxe)/Stars Hollow - It%27s Not That.mp3",
      "ranked_modes": [
        "osu"
      ],
      "beatmapset_ids_by_mode": {
        "osu": [
          1714779
        ]
      }
    },
    {
      "title": "Out the Sunroof.",
      "preview": "https://assets.ppy.sh/artists/353/I Want to Live My Life/Stars Hollow - Out the Sunroof..mp3",
      "ranked_modes": [
        "taiko"
      ],
      "beatmapset_ids_by_mode": {
        "taiko": [
          1968973
        ]
      }
    },
    {
      "title": "Beside You.",
      "preview": "https://assets.ppy.sh/artists/353/I Want to Live My Life/Stars Hollow - Beside You..mp3",
      "ranked_modes": [],
      "beatmapset_ids_by_mode": {}
    },
    {
      "title": "Drinking Buddies",
      "preview": "https://assets.ppy.sh/artists/353/I%27m Really Not That Upset About It/Stars Hollow - Drinking Buddies.mp3",
      "ranked_modes": [],
      "beatmapset_ids_by_mode": {}
    },
    {
      "title": "Stuck to You.",
      "preview": "https://assets.ppy.sh/artists/353/I Want to Live My Life/Stars Hollow - Stuck to You..mp3",
      "ranked_modes": [],
      "beatmapset_ids_by_mode": {}
    },
    {
      "title": "Tadpole",
      "preview": "https://assets.ppy.sh/artists/353/Happy Again (Deluxe)/Stars Hollow - Tadpole.mp3",
      "ranked_modes": [],
      "beatmapset_ids_by_mode": {}
    },
    {
      "title": "With Weight.",
      "preview": "https://assets.ppy.sh/artists/353/I Want to Live My Life/Stars Hollow - With Weight..mp3",
      "ranked_modes": [],
      "beatmapset_ids_by_mode": {}
    },
    {
      "title": "you won't be happy again",
      "preview": "https://assets.ppy.sh/artists/353/Happy Again (Deluxe)/Stars Hollow - you won%27t be happy again.mp3",
      "ranked_modes": [],
      "beatmapset_ids_by_mode": {}
    }
  ],
  "updated_at": "2026-04-02T22:20:08Z"
}