{
  "id": 499,
  "name": "Xeon Diversity",
  "tracks": [
    {
      "title": "Luminaire",
      "preview": "https://assets.ppy.sh/artists/499/Genesis EP/Xeon Diversity - Luminaire.mp3",
      "ranked_modes": [
        "osu"
      ],
      "beatmapset_ids_by_mode": {
        "osu": [
          2353640
        ]
      }
    },
    {
      "title": "Cheerful",
      "preview": "https://assets.ppy.sh/artists/499/Songs/Xeon Diversity - Cheerful.mp3",
      "ranked_modes": [],
      "beatmapset_ids_by_mode": {}
    },
    {
      "title": "Cosmic Adventure",
      "preview": "https://assets.ppy.sh/artists/499/Songs/Xeon Diversity - Cosmic Adventure.mp3",
      "ranked_modes": [],
      "beatmapset_ids_by_mode": {}
    },
    {
      "title": "Enough",
      "preview": "https://assets.ppy.sh/artists/499/Songs/Xeon Diversity - Enough.mp3",
      "ranked_modes": [],
      "beatmapset_ids_by_mode": {}
    },
    {
      "title": "For You",
      "preview": "https://assets.ppy.sh/artists/499/Songs/Xeon Diversity - For You.mp3",
      "ranked_modes": [],
      "beatmapset_ids_by_mode": {}
    },
    {
      "title": "Game Start",
      "preview": "https://assets.ppy.sh/artists/499/Songs/Xeon Diversity - Game Start.mp3",
      "ranked_modes": [],
      "beatmapset_ids_by_mode": {}
    },
    {
      "title": "Kanade (feat. Mariela Riona)",
      "preview": "https://assets.ppy.sh/artists/499/Cursed of the Origin EP/Xeon Diversity - Kanade (feat. Mariela Riona).mp3",
      "ranked_modes": [],
      "beatmapset_ids_by_mode": {}
    },
    {
      "title": "Let's Go !",
      "preview": "https://assets.ppy.sh/artists/499/Songs/Xeon Diversity - Let%27s Go !.mp3",
      "ranked_modes": [],
      "beatmapset_ids_by_mode": {}
    },
    {
      "title": "Never Give Up",
      "preview": "https://assets.ppy.sh/artists/499/Songs/Xeon Diversity - Never Give Up.mp3",
      "ranked_modes": [],
      "beatmapset_ids_by_mode": {}
    },
    {
      "title": "Play !",
      "preview": "https://assets.ppy.sh/artists/499/Songs/Xeon Diversity - Play !.mp3",
      "ranked_modes": [],
      "beatmapset_ids_by_mode": {}
    },
    {
      "title": "Time",
      "preview": "https://assets.ppy.sh/artists/499/Songs/Xeon Diversity - Time.mp3",
      "ranked_modes": [],
      "beatmapset_ids_by_mode": {}
    },
    {
      "title": "Yosha",
      "preview": "https://assets.ppy.sh/artists/499/Yosha/Xeon Diversity - Yosha.mp3",
      "ranked_modes": [],
      "beatmapset_ids_by_mode": {}
    }
  ],
  "updated_at": "2026-04-02T03:50:32Z"
}