{
  "id": 73,
  "name": "LeaF",
  "tracks": [
    {
      "title": "Aleph-0",
      "preview": "https://assets.ppy.sh/artists/73/previews/1980.mp3",
      "ranked_modes": [
        "mania",
        "osu",
        "taiko"
      ],
      "beatmapset_ids_by_mode": {
        "mania": [
          2406499
        ],
        "taiko": [
          2166675
        ],
        "osu": [
          1364626
        ]
      }
    },
    {
      "title": "Aleph-0 (extended ver.)",
      "preview": "https://assets.ppy.sh/artists/73/previews/1979.mp3",
      "ranked_modes": [
        "mania"
      ],
      "beatmapset_ids_by_mode": {
        "mania": [
          1234605,
          1800224,
          2154452
        ]
      }
    },
    {
      "title": "Alice in Misanthrope -Ensei Alice-",
      "preview": "https://assets.ppy.sh/artists/73/previews/1981.mp3",
      "ranked_modes": [
        "fruits",
        "mania",
        "osu",
        "taiko"
      ],
      "beatmapset_ids_by_mode": {
        "fruits": [
          797236
        ],
        "osu": [
          588475,
          782989
        ],
        "taiko": [
          523315
        ],
        "mania": [
          520399
        ]
      }
    },
    {
      "title": "Arianrhod",
      "preview": "https://assets.ppy.sh/artists/73/previews/1982.mp3",
      "ranked_modes": [
        "mania",
        "osu",
        "taiko"
      ],
      "beatmapset_ids_by_mode": {
        "osu": [
          1156514,
          1163990,
          1174631
        ],
        "taiko": [
          1128939
        ],
        "mania": [
          366362
        ]
      }
    },
    {
      "title": "ATHAZA",
      "preview": "https://assets.ppy.sh/artists/73/previews/1978.mp3",
      "ranked_modes": [
        "mania"
      ],
      "beatmapset_ids_by_mode": {
        "mania": [
          1154007
        ]
      }
    },
    {
      "title": "Calamity Fortune",
      "preview": "https://assets.ppy.sh/artists/73/previews/1984.mp3",
      "ranked_modes": [
        "fruits",
        "mania",
        "osu",
        "taiko"
      ],
      "beatmapset_ids_by_mode": {
        "mania": [
          2288990
        ],
        "osu": [
          96103,
          359168,
          2123533
        ],
        "taiko": [
          96103,
          1603159,
          1809241
        ],
        "fruits": [
          114741
        ]
      }
    },
    {
      "title": "Calamity Fortune (extended ver.)",
      "preview": "https://assets.ppy.sh/artists/73/previews/1983.mp3",
      "ranked_modes": [
        "fruits",
        "mania",
        "osu",
        "taiko"
      ],
      "beatmapset_ids_by_mode": {
        "taiko": [
          1350080,
          2009925
        ],
        "mania": [
          1711883
        ],
        "osu": [
          1626172
        ],
        "fruits": [
          834516,
          1180607
        ]
      }
    },
    {
      "title": "Chronostasis",
      "preview": "https://assets.ppy.sh/artists/73/previews/1985.mp3",
      "ranked_modes": [
        "taiko"
      ],
      "beatmapset_ids_by_mode": {
        "taiko": [
          193469
        ]
      }
    },
    {
      "title": "Doppelganger",
      "preview": "https://assets.ppy.sh/artists/73/previews/1987.mp3",
      "ranked_modes": [
        "mania",
        "taiko"
      ],
      "beatmapset_ids_by_mode": {
        "mania": [
          407153,
          2352480
        ],
        "taiko": [
          299136,
          1130071,
          1239213
        ]
      }
    },
    {
      "title": "Doppelganger (extended ver.)",
      "preview": "https://assets.ppy.sh/artists/73/previews/1986.mp3",
      "ranked_modes": [
        "fruits",
        "mania",
        "taiko"
      ],
      "beatmapset_ids_by_mode": {
        "mania": [
          1980729
        ],
        "taiko": [
          833092
        ],
        "fruits": [
          2297358
        ]
      }
    },
    {
      "title": "Evanescent",
      "preview": "https://assets.ppy.sh/artists/73/previews/1989.mp3",
      "ranked_modes": [
        "fruits",
        "mania",
        "osu",
        "taiko"
      ],
      "beatmapset_ids_by_mode": {
        "mania": [
          2439440
        ],
        "taiko": [
          2405842
        ],
        "osu": [
          227126,
          227234,
          440997
        ],
        "fruits": [
          440997
        ]
      }
    },
    {
      "title": "Evanescent (extended ver.)",
      "preview": "https://assets.ppy.sh/artists/73/previews/1988.mp3",
      "ranked_modes": [
        "fruits",
        "osu",
        "taiko"
      ],
      "beatmapset_ids_by_mode": {
        "taiko": [
          1890900
        ],
        "fruits": [
          1784479
        ],
        "osu": [
          1057706
        ]
      }
    },
    {
      "title": "I",
      "preview": "https://assets.ppy.sh/artists/73/previews/1991.mp3",
      "ranked_modes": [
        "mania",
        "osu",
        "taiko"
      ],
      "beatmapset_ids_by_mode": {
        "taiko": [
          1128580
        ],
        "mania": [
          426638
        ],
        "osu": [
          99244
        ]
      }
    },
    {
      "title": "Kyouki Ranbu",
      "preview": "https://assets.ppy.sh/artists/73/previews/1993.mp3",
      "ranked_modes": [
        "fruits",
        "mania",
        "osu",
        "taiko"
      ],
      "beatmapset_ids_by_mode": {
        "mania": [
          2194386
        ],
        "fruits": [
          1939741
        ],
        "osu": [
          1312129
        ],
        "taiko": [
          394552
        ]
      }
    },
    {
      "title": "Kyouki Ranbu (extended ver.)",
      "preview": "https://assets.ppy.sh/artists/73/previews/1992.mp3",
      "ranked_modes": [
        "fruits",
        "osu",
        "taiko"
      ],
      "beatmapset_ids_by_mode": {
        "osu": [
          1371373,
          1600135,
          2527681
        ],
        "fruits": [
          1410668,
          1445309
        ],
        "taiko": [
          1154434,
          1158149
        ]
      }
    },
    {
      "title": "MARENOL",
      "preview": "https://assets.ppy.sh/artists/73/previews/1995.mp3",
      "ranked_modes": [
        "mania",
        "osu",
        "taiko"
      ],
      "beatmapset_ids_by_mode": {
        "mania": [
          2424356
        ],
        "osu": [
          1070820,
          1136149
        ],
        "taiko": [
          966590
        ]
      }
    },
    {
      "title": "MEPHISTO",
      "preview": "https://assets.ppy.sh/artists/73/previews/1996.mp3",
      "ranked_modes": [
        "fruits",
        "mania",
        "osu",
        "taiko"
      ],
      "beatmapset_ids_by_mode": {
        "taiko": [
          106212,
          2194538
        ],
        "osu": [
          106212,
          714024
        ],
        "mania": [
          106212
        ],
        "fruits": [
          106212
        ]
      }
    },
    {
      "title": "Mopemope",
      "preview": "https://assets.ppy.sh/artists/73/previews/2001.mp3",
      "ranked_modes": [
        "mania",
        "osu",
        "taiko"
      ],
      "beatmapset_ids_by_mode": {
        "osu": [
          1097600,
          1174616,
          2063704
        ],
        "mania": [
          1154288
        ],
        "taiko": [
          1128384
        ]
      }
    },
    {
      "title": "Poison AND/OR Affection",
      "preview": "https://assets.ppy.sh/artists/73/previews/2003.mp3",
      "ranked_modes": [
        "osu",
        "taiko"
      ],
      "beatmapset_ids_by_mode": {
        "osu": [
          1130436
        ],
        "taiko": [
          245517
        ]
      }
    },
    {
      "title": "Wizdomiot",
      "preview": "https://assets.ppy.sh/artists/73/previews/2005.mp3",
      "ranked_modes": [
        "fruits",
        "mania",
        "osu",
        "taiko"
      ],
      "beatmapset_ids_by_mode": {
        "fruits": [
          1128274
        ],
        "mania": [
          592272
        ],
        "taiko": [
          352682
        ],
        "osu": [
          336099
        ]
      }
    },
    {
      "title": "Wizdomiot (extended ver.)",
      "preview": "https://assets.ppy.sh/artists/73/previews/2004.mp3",
      "ranked_modes": [
        "fruits",
        "mania",
        "osu",
        "taiko"
      ],
      "beatmapset_ids_by_mode": {
        "mania": [
          1360248
        ],
        "osu": [
          1220268,
          2305788
        ],
        "fruits": [
          1155135
        ],
        "taiko": [
          988522
        ]
      }
    },
    {
      "title": "ATHAZA (extended ver.)",
      "preview": "https://assets.ppy.sh/artists/73/previews/1977.mp3",
      "ranked_modes": [],
      "beatmapset_ids_by_mode": {}
    },
    {
      "title": "Heterochromia Iridis",
      "preview": "https://assets.ppy.sh/artists/73/previews/1976.mp3",
      "ranked_modes": [],
      "beatmapset_ids_by_mode": {}
    },
    {
      "title": "I (extended ver.)",
      "preview": "https://assets.ppy.sh/artists/73/previews/1990.mp3",
      "ranked_modes": [],
      "beatmapset_ids_by_mode": {}
    },
    {
      "title": "Lyrith -Meikyuu Lilith-",
      "preview": "https://assets.ppy.sh/artists/73/previews/1994.mp3",
      "ranked_modes": [],
      "beatmapset_ids_by_mode": {}
    },
    {
      "title": "Melhenia -malchenia-",
      "preview": "https://assets.ppy.sh/artists/73/previews/1997.mp3",
      "ranked_modes": [],
      "beatmapset_ids_by_mode": {}
    },
    {
      "title": "Mere Fancy",
      "preview": "https://assets.ppy.sh/artists/73/previews/1999.mp3",
      "ranked_modes": [],
      "beatmapset_ids_by_mode": {}
    },
    {
      "title": "Mere Fancy (extended ver.)",
      "preview": "https://assets.ppy.sh/artists/73/previews/1998.mp3",
      "ranked_modes": [],
      "beatmapset_ids_by_mode": {}
    },
    {
      "title": "Mopemope (extended ver.)",
      "preview": "https://assets.ppy.sh/artists/73/previews/2000.mp3",
      "ranked_modes": [],
      "beatmapset_ids_by_mode": {}
    },
    {
      "title": "Poison AND/OR Affection (extended ver.)",
      "preview": "https://assets.ppy.sh/artists/73/previews/2002.mp3",
      "ranked_modes": [],
      "beatmapset_ids_by_mode": {}
    }
  ],
  "updated_at": "2026-04-02T22:02:34Z"
}